LICENSE
README.md
pysqlitekg2vec/__init__.py
pysqlitekg2vec/connectors.py
pysqlitekg2vec/embedders/__init__.py
pysqlitekg2vec/embedders/embedder.py
pysqlitekg2vec/embedders/fasttext.py
pysqlitekg2vec/embedders/word2vec.py
pysqlitekg2vec/graphs/__init__.py
pysqlitekg2vec/graphs/io.py
pysqlitekg2vec/graphs/kg.py
pysqlitekg2vec/graphs/lmdb/__init__.py
pysqlitekg2vec/graphs/lmdb/lmdbkg.py
pysqlitekg2vec/graphs/sqlite/__init__.py
pysqlitekg2vec/graphs/sqlite/sqlitekg.py
pysqlitekg2vec/graphs/types.py
pysqlitekg2vec/graphs/vertex.py
pysqlitekg2vec/rdf2vec.py
pysqlitekg2vec/samplers/__init__.py
pysqlitekg2vec/samplers/frequency.py
pysqlitekg2vec/samplers/pagerank.py
pysqlitekg2vec/samplers/sampler.py
pysqlitekg2vec/samplers/uniform.py
pysqlitekg2vec/samplers/wide.py
pysqlitekg2vec/typings.py
pysqlitekg2vec/utils/__init__.py
pysqlitekg2vec/utils/validation.py
pysqlitekg2vec/walkers/__init__.py
pysqlitekg2vec/walkers/anonymous.py
pysqlitekg2vec/walkers/community.py
pysqlitekg2vec/walkers/halk.py
pysqlitekg2vec/walkers/ngram.py
pysqlitekg2vec/walkers/random.py
pysqlitekg2vec/walkers/split.py
pysqlitekg2vec/walkers/vault/__init__.py
pysqlitekg2vec/walkers/vault/sqlitevault.py
pysqlitekg2vec/walkers/vault/vault.py
pysqlitekg2vec/walkers/walker.py
pysqlitekg2vec/walkers/walklet.py
pysqlitekg2vec/walkers/weisfeiler_lehman.py
pysqlitekg2vec-1.0.0.dist-info/LICENSE
pysqlitekg2vec-1.0.0.dist-info/WHEEL
pysqlitekg2vec-1.0.0.dist-info/METADATA
pysqlitekg2vec-1.0.0.dist-info/RECORD
