Metadata-Version: 2.1
Name: pysqlitekg2vec
Version: 1.0.0
Summary: Python implementation and extension of RDF2Vec
Home-page: https://github.com/CollabRec/pysqlitekg2vec
License: Ghent University and IMEC vzw
Keywords: embeddings,knowledge-graph,rdf2vec,word2vec
Author: Gilles Vandewiele
Author-email: gilles.vandewiele@ugent.be
Maintainer: CollabRec
Maintainer-email: collabrecommendation@gmail.com
Requires-Python: >=3.8,<4.0
Classifier: Development Status :: 3 - Alpha
Classifier: Intended Audience :: Developers
Classifier: License :: Other/Proprietary License
Classifier: Operating System :: OS Independent
Classifier: Programming Language :: Python :: 3
Classifier: Programming Language :: Python :: 3.8
Classifier: Programming Language :: Python :: 3.9
Classifier: Programming Language :: Python :: 3.10
Classifier: Programming Language :: Python :: 3.11
Classifier: Programming Language :: Python :: 3.7
Classifier: Programming Language :: Python :: 3.8
Classifier: Programming Language :: Python :: 3.9
Classifier: Topic :: Software Development :: Build Tools
Provides-Extra: docs
Provides-Extra: lint
Provides-Extra: tests
Requires-Dist: aiohttp (>=3.8.1,<4.0.0) ; extra == "tests"
Requires-Dist: attrs (>=21.2,<23.0)
Requires-Dist: cachetools (>=5.0.0,<6.0.0)
Requires-Dist: gensim (>=4.0.1,<5.0.0) ; extra == "docs" or extra == "tests"
Requires-Dist: matplotlib (>=3.4.2,<4.0.0)
Requires-Dist: nest-asyncio (>=1.5.1,<2.0.0) ; extra == "tests"
Requires-Dist: nest_asyncio (>=1.5.4,<2.0.0) ; extra == "tests"
Requires-Dist: networkx (>=2.8,<3.0)
Requires-Dist: numpy (>=1.22.3,<2.0.0) ; extra == "tests"
Requires-Dist: pandas (>=1.4.2,<2.0.0) ; extra == "tests"
Requires-Dist: python-Levenshtein (>=0.12.2,<0.13.0)
Requires-Dist: python-louvain (>=0.16,<0.17)
Requires-Dist: rdflib (>=6.1.1,<7.0.0) ; extra == "docs" or extra == "tests"
Requires-Dist: scikit-learn (>=1.0.2,<2.0.0) ; extra == "docs"
Requires-Dist: sortedcontainers (>=2.4.0,<3.0.0)
Requires-Dist: toml (>=0.10.2,<0.11.0) ; extra == "docs"
Requires-Dist: torch (>=1.8.1,<2.0.0)
Project-URL: Repository, https://github.com/CollabRec/pysqlitekg2vec
